py_pkg/__init__.py
py_pkg/__version__.py
odinwolf-1.1.6.dist-info/LICENSE
odinwolf-1.1.6.dist-info/METADATA
odinwolf-1.1.6.dist-info/WHEEL
odinwolf-1.1.6.dist-info/entry_points.txt
odinwolf-1.1.6.dist-info/top_level.txt
odinwolf-1.1.6.dist-info/RECORD
